aoirint_matvtool/__init__.py
aoirint_matvtool/__main__.py
aoirint_matvtool/cli.py
aoirint_matvtool/config.py
aoirint_matvtool/util.py
aoirint_matvtool/command/__init__.py
aoirint_matvtool/command/audio.py
aoirint_matvtool/command/crop_scale.py
aoirint_matvtool/command/find_image.py
aoirint_matvtool/command/fps.py
aoirint_matvtool/command/key_frames.py
aoirint_matvtool/command/select_audio.py
aoirint_matvtool/command/slice.py
aoirint_matvtool/progress_handler/__init__.py
aoirint_matvtool/progress_handler/base.py
aoirint_matvtool/progress_handler/plain.py
aoirint_matvtool/progress_handler/tqdm.py
aoirint_matvtool/progress_handler/utility/__init__.py
aoirint_matvtool/progress_handler/utility/progress_calculator.py
aoirint_matvtool/utility/__init__.py
aoirint_matvtool/utility/async_subprocess_helper.py
aoirint_matvtool/utility/key_frame_time_fitter.py
aoirint_matvtool/video_utility/__init__.py
aoirint_matvtool/video_utility/audio_selector.py
aoirint_matvtool/video_utility/audio_track_title_parser.py
aoirint_matvtool/video_utility/crop_scaler.py
aoirint_matvtool/video_utility/fps_parser.py
aoirint_matvtool/video_utility/image_finder.py
aoirint_matvtool/video_utility/key_frame_parser.py
aoirint_matvtool/video_utility/video_slicer.py
aoirint_matvtool-0.7.0.dist-info/licenses/LICENSE
aoirint_matvtool-0.7.0.dist-info/METADATA
aoirint_matvtool-0.7.0.dist-info/WHEEL
aoirint_matvtool-0.7.0.dist-info/entry_points.txt
aoirint_matvtool-0.7.0.dist-info/top_level.txt
aoirint_matvtool-0.7.0.dist-info/RECORD
