Metadata-Version: 2.4
Name: aoirint-matvtool
Version: 0.7.0
Summary: A command line tool to handle a multi audio track video file
Author-email: aoirint <aoirint@gmail.com>
Maintainer-email: aoirint <aoirint@gmail.com>
License-Expression: MIT
Project-URL: Repository, https://github.com/aoirint/matvtoolpy
Requires-Python: >=3.11
License-File: LICENSE
Requires-Dist: pydantic>=2.11.9
Requires-Dist: tqdm>=4.67.1
Dynamic: license-file
